parsee/__init__.py
parsee/chat/custom_dataclasses.py
parsee/chat/main.py
parsee/cloud/api.py
parsee/cloud/cloud_file_manager.py
parsee/cloud/cloud_image_fetcher.py
parsee/converters/__init__.py
parsee/converters/html_extraction.py
parsee/converters/image_creation.py
parsee/converters/interfaces.py
parsee/converters/json_to_raw.py
parsee/converters/langchain.py
parsee/converters/main.py
parsee/converters/pdf_extraction.py
parsee/converters/simple_text.py
parsee/datasets/dataset_dataclasses.py
parsee/datasets/evaluation/main.py
parsee/datasets/main.py
parsee/datasets/readers/disk_reader.py
parsee/datasets/readers/interfaces.py
parsee/datasets/writers/disk_writer.py
parsee/datasets/writers/interfaces.py
parsee/extraction/__init__.py
parsee/extraction/extractor_dataclasses.py
parsee/extraction/extractor_elements.py
parsee/extraction/final_structuring.py
parsee/extraction/models/__init__.py
parsee/extraction/models/helpers.py
parsee/extraction/models/llm_models/__init__.py
parsee/extraction/models/llm_models/llm_base_model.py
parsee/extraction/models/llm_models/model_collection/anthropic_model.py
parsee/extraction/models/llm_models/model_collection/chatgpt_model.py
parsee/extraction/models/llm_models/model_collection/cohere_model.py
parsee/extraction/models/llm_models/model_collection/google_model.py
parsee/extraction/models/llm_models/model_collection/mistral_model.py
parsee/extraction/models/llm_models/model_collection/ollama_model.py
parsee/extraction/models/llm_models/model_collection/replicate_model.py
parsee/extraction/models/llm_models/model_collection/together_model.py
parsee/extraction/models/llm_models/prompts.py
parsee/extraction/models/llm_models/structuring_schema.py
parsee/extraction/models/model_dataclasses.py
parsee/extraction/models/model_loader.py
parsee/extraction/run.py
parsee/extraction/tasks/__init__.py
parsee/extraction/tasks/element_classification/__init__.py
parsee/extraction/tasks/element_classification/element_model.py
parsee_core-0.1.8.5.dist-info/LICENSE
parsee_core-0.1.8.5.dist-info/METADATA
parsee_core-0.1.8.5.dist-info/WHEEL
parsee_core-0.1.8.5.dist-info/RECORD
