Metadata-Version: 2.3
Name: parsee-core
Version: 0.1.8.5
Summary: 
Home-page: https://parsee.ai
Author: Parsee.ai
Author-email: info@parsee.ai
Requires-Python: >=3.9,<3.11
Classifier: Programming Language :: Python :: 3
Classifier: Programming Language :: Python :: 3.9
Classifier: Programming Language :: Python :: 3.10
Requires-Dist: anthropic (>=0.20.0,<0.21.0)
Requires-Dist: beautifulsoup4 (>=4.11.1,<5.0.0)
Requires-Dist: cohere (>=5.3.3,<6.0.0)
Requires-Dist: google-genai (>=1.26.0,<2.0.0)
Requires-Dist: lxml (>=4.9.1,<5.0.0)
Requires-Dist: mistralai (>=1.1.0,<2.0.0)
Requires-Dist: numpy (>=1.23.1,<2.0.0)
Requires-Dist: ollama (>0.1.7)
Requires-Dist: openai (>=2.13.0,<3.0.0)
Requires-Dist: opencv-python (>=4.9.0.80,<5.0.0.0)
Requires-Dist: pandas (>=1.4.3,<2.0.0)
Requires-Dist: parsee-pdf-reader (>=0.1.8.2,<0.2.0.0)
Requires-Dist: pydantic (>=2.7.0,<3.0.0)
Requires-Dist: pydantic-settings (>=2.6.1,<3.0.0)
Requires-Dist: replicate (>=0.23.1,<0.24.0)
Requires-Dist: requests (>=2.28.1,<3.0.0)
Requires-Dist: scikit-learn (>=1.5.2,<2.0.0)
Requires-Dist: sentence-transformers (>=2.7,<3.0)
Requires-Dist: tenacity (>=8.1.0,<9.0.0)
Requires-Dist: tiktoken (>=0.4.0,<0.5.0)
Requires-Dist: together (>=1.1.1,<2.0.0)
Requires-Dist: torch (<2.3)
Requires-Dist: transformers (>=4.47.1,<4.50)
Requires-Dist: urllib3 (<2)
